wintersdeep/argparse/__init__.py
wintersdeep/argparse/argument_parser.py
wintersdeep/argparse/log_level_action.py
wintersdeep/argparse/logging_configuration.py
wintersdeep/argparse/mapping_choices_action.py
wintersdeep.argparse-1.1.4.dist-info/LICENCE
wintersdeep.argparse-1.1.4.dist-info/METADATA
wintersdeep.argparse-1.1.4.dist-info/WHEEL
wintersdeep.argparse-1.1.4.dist-info/top_level.txt
wintersdeep.argparse-1.1.4.dist-info/RECORD
