Metadata-Version: 2.1
Name: wintersdeep.argparse
Version: 1.1.4
Summary: Extends the native Python3 `argparse.ArgumentParser` to supports using maps as a `choices` argument type.
Home-page: https://github.com/wintersdeep/wintersdeep_argparse
Author: WintersDeep
Author-email: admin@wintersdeep.com
Requires-Python: >=3.11, <4
License-File: LICENCE
